stakeshare/__init__.py
stakeshare/client.py
stakeshare/errors.py
stakeshare/utils.py
stakeshare-0.1b0.dist-info/METADATA
stakeshare-0.1b0.dist-info/WHEEL
stakeshare-0.1b0.dist-info/top_level.txt
stakeshare-0.1b0.dist-info/RECORD
