Metadata-Version: 2.1
Name: stakeshare
Version: 0.1b0
Summary: StakeShare RPC client
Home-page: https://github.com/mrmm/stakeshare-python
Author: Ronittos
Author-email: ronittos.dorittoss@gmail.com
License: Apache 2.0
Platform: UNKNOWN
